gatul/__init__.py
gatul-0.0.1.dist-info/METADATA
gatul-0.0.1.dist-info/WHEEL
gatul-0.0.1.dist-info/top_level.txt
gatul-0.0.1.dist-info/RECORD
